langflow_cli/__init__.py
langflow_cli/api_client.py
langflow_cli/cli.py
langflow_cli/config.py
langflow_cli/flow_checks.py
langflow_cli/git_client.py
langflow_cli/git_config.py
langflow_cli/utils.py
langflow_cli/commands/__init__.py
langflow_cli/commands/env.py
langflow_cli/commands/flows.py
langflow_cli/commands/git.py
langflow_cli/commands/projects.py
langflow_cli/commands/settings.py
langflow_cli/commands/status.py
langflow_cli-0.1.4.dist-info/METADATA
langflow_cli-0.1.4.dist-info/WHEEL
langflow_cli-0.1.4.dist-info/entry_points.txt
langflow_cli-0.1.4.dist-info/licenses/LICENSE
langflow_cli-0.1.4.dist-info/RECORD
