Metadata-Version: 2.4
Name: langflow-cli
Version: 0.1.4
Summary: CLI tool for managing Langflow environments and resources
Project-URL: Homepage, https://github.com/smatiolids/langflow-cli
Project-URL: Documentation, https://github.com/smatiolids/langflow-cli#readme
Project-URL: Repository, https://github.com/smatiolids/langflow-cli
Project-URL: Issues, https://github.com/smatiolids/langflow-cli/issues
Author-email: Samuel Matioli <smatioli@gmail.com>
License: MIT
License-File: LICENSE
Keywords: api,automation,cli,langchain,langflow,workflow
Classifier: Development Status :: 4 - Beta
Classifier: Intended Audience :: Developers
Classifier: Intended Audience :: System Administrators
Classifier: License :: OSI Approved :: MIT License
Classifier: Operating System :: OS Independent
Classifier: Programming Language :: Python :: 3
Classifier: Programming Language :: Python :: 3.8
Classifier: Programming Language :: Python :: 3.9
Classifier: Programming Language :: Python :: 3.10
Classifier: Programming Language :: Python :: 3.11
Classifier: Programming Language :: Python :: 3.12
Classifier: Topic :: Software Development :: Libraries :: Python Modules
Classifier: Topic :: System :: Systems Administration
Classifier: Topic :: Utilities
Requires-Python: >=3.8
Requires-Dist: click>=8.0.0
Requires-Dist: pygithub>=2.0.0
Requires-Dist: requests>=2.28.0
Requires-Dist: rich>=13.0.0
Provides-Extra: dev
Requires-Dist: build>=1.0.0; extra == 'dev'
Requires-Dist: pytest-cov>=4.0.0; extra == 'dev'
Requires-Dist: pytest-mock>=3.10.0; extra == 'dev'
Requires-Dist: pytest>=7.0.0; extra == 'dev'
Requires-Dist: twine>=4.0.0; extra == 'dev'
